identifiability/__init__.py
identifiability/version.py
identifiability-0.5.0.dist-info/licenses/LICENSE
identifiability-0.5.0.dist-info/METADATA
identifiability-0.5.0.dist-info/WHEEL
identifiability-0.5.0.dist-info/top_level.txt
identifiability-0.5.0.dist-info/RECORD
