Metadata-Version: 2.4
Name: identifiability
Version: 0.5.0
Summary: Parameter identifiability analysis in Python
Author-email: "Johann M. Rohwer" <j.m.rohwer@gmail.com>
License-Expression: BSD-3-Clause
Project-URL: Homepage, https://github.com/jmrohwer/identifiability/
Project-URL: Download, https://github.com/jmrohwer/identifiability/archive/refs/tags/v0.5.0.zip
Keywords: identifiability,parameter analysis,bioinformatics
Classifier: Development Status :: 5 - Production/Stable
Classifier: Environment :: Console
Classifier: Intended Audience :: End Users/Desktop
Classifier: Intended Audience :: Science/Research
Classifier: Operating System :: OS Independent
Classifier: Programming Language :: Python
Classifier: Programming Language :: Python :: 3.9
Classifier: Programming Language :: Python :: 3.10
Classifier: Programming Language :: Python :: 3.11
Classifier: Programming Language :: Python :: 3.12
Classifier: Programming Language :: Python :: 3.13
Classifier: Topic :: Scientific/Engineering :: Bio-Informatics
Requires-Python: >=3.9
License-File: LICENSE
Requires-Dist: numpy
Requires-Dist: scipy
Requires-Dist: matplotlib
Requires-Dist: lmfit
Provides-Extra: pyscesmp
Requires-Dist: pysces; extra == "pyscesmp"
Requires-Dist: multiprocessing_on_dill; extra == "pyscesmp"
Dynamic: license-file
